napalm_aruba505/__init__.py
napalm_aruba505/aruba505.py
napalm_aruba505-0.0.172.dist-info/LICENSE
napalm_aruba505-0.0.172.dist-info/METADATA
napalm_aruba505-0.0.172.dist-info/WHEEL
napalm_aruba505-0.0.172.dist-info/top_level.txt
napalm_aruba505-0.0.172.dist-info/RECORD
