Metadata-Version: 2.1
Name: napalm_aruba505
Version: 0.0.172
Summary: Napalm Aruba driver for ArubaOS Wi-Fi devices '505' 
Home-page: https://github.com/skarpe-github/napalm-aruba505
Author: David Johnnes, Sonja Karpe
Author-email: david.johnnes@gmail.com
License: Apache 2
Keywords: napalm drive
Classifier: Topic :: Utilities
Classifier: Programming Language :: Python :: 3
Classifier: Operating System :: OS Independent
Classifier: License :: OSI Approved :: Apache Software License
License-File: LICENSE
